{
  "id": "asvow.app.sub",
  "name": "AsVow应用订阅",
  "author": "@AsVow",
  "icon": "https://avatars.githubusercontent.com/u/88471740",
  "repo": "https://ooxx.be/js",
  "apps": [
    {
      "id": "ksjsb",
      "name": "快手",
      "keys": ["@ksjsb.ksjsbCookie"],
      "author": "@AsVow",
      "repo": "https://ooxx.be/js",
      "icons": ["https://ooxx.be/js/icon/umer-trn.png", "https://ooxx.be/js/icon/umer.png"],
      "script": "https://ooxx.be/js/umer.js"
    },
    {
      "id": "jegotrip",
      "name": "无忧行",
      "keys": ["@无忧行.AsVow"],
      "author": "@AsVow",
      "repo": "https://ooxx.be/js",
      "icons": ["https://ooxx.be/js/icon/jegotrip-trn.png", "https://ooxx.be/js/icon/jegotrip.png"],
      "script": "https://ooxx.be/js/jegotrip.js"
    }
  ]
}
